<?xml version="1.0"?>
<unit xmlns:xsi="http://www.w3.org/2001/XMLSchema-instance"
xmlns:rs="http://www.ribbonsoft.com">
  <class name="RSpatialIndexVisitorAdapter"
  xsi:noNamespaceSchemaLocation="../class.xsd" isCopyable="false"
  hasShell="true" sharedPointerSupport="false" isQObject="false"
  hasStreamOperator="false" isAbstract="false" isScriptable="true">
    <baseClass name="RSpatialIndexVisitor" specifier="public" />
    <method name="visitData" cppName="visitData" specifier="public"
    isStatic="false" isVirtual="true" isScriptOverwritable="true">
      <variant returnType="void" isPureVirtual="false">
        <arg type="int" typeName="int" name="id" isConst="false" />
        <arg type="int" typeName="int" name="pos"
        isConst="false" />
        <arg type="double" typeName="double" name="x1"
        isConst="false" />
        <arg type="double" typeName="double" name="y1"
        isConst="false" />
        <arg type="double" typeName="double" name="z1"
        isConst="false" />
        <arg type="double" typeName="double" name="x2"
        isConst="false" />
        <arg type="double" typeName="double" name="y2"
        isConst="false" />
        <arg type="double" typeName="double" name="z2"
        isConst="false" />
      </variant>
    </method>
    <method name="visitNode" cppName="visitNode" specifier="public"
    isStatic="false" isVirtual="true" isScriptOverwritable="true">
      <variant returnType="void" isPureVirtual="false">
        <arg type="double" typeName="double" name="x1"
        isConst="false" />
        <arg type="double" typeName="double" name="y1"
        isConst="false" />
        <arg type="double" typeName="double" name="z1"
        isConst="false" />
        <arg type="double" typeName="double" name="x2"
        isConst="false" />
        <arg type="double" typeName="double" name="y2"
        isConst="false" />
        <arg type="double" typeName="double" name="z2"
        isConst="false" />
      </variant>
    </method>
  </class>
</unit>
